euler_math/__init__.py
euler_math/euler.py
euler_math/list.py
euler_math/seq.py
euler_math/tco.py
euler_math-0.4.6.dist-info/LICENSE
euler_math-0.4.6.dist-info/WHEEL
euler_math-0.4.6.dist-info/METADATA
euler_math-0.4.6.dist-info/RECORD
